resik/__init__.py
resik/__main__.py
resik/app.py
resik-0.0.7.dist-info/LICENSE
resik-0.0.7.dist-info/METADATA
resik-0.0.7.dist-info/WHEEL
resik-0.0.7.dist-info/top_level.txt
resik-0.0.7.dist-info/RECORD
