Metadata-Version: 2.1
Name: resik
Version: 0.0.7
Summary: Description about the project.
Author: Master
Author-email: name@email.com
License: License
License-File: LICENSE
Requires-Dist: tk
